[
  {"title": "Gasthaus", "key": "Trattoria", "icon": "deu/WineAndFood_Trattoria.png"},
{"title": "Denkmäler", "key": "Monument_location", "icon": "deu/CulturalActivity_Monument_location.png"},
{"title": "Restaurants", "key": "Restaurant", "icon": "deu/WineAndFood_Restaurant.png"},
{"title": "Museum", "key": "Museum", "icon": "deu/CulturalActivity_Museum.png"},
{"title": "Kirchen", "key": "Churches", "icon": "deu/CulturalActivity_Churches.png"},
{"title": "Pizzeria", "key": "Pizzeria", "icon": "deu/WineAndFood_Pizzeria.png"},
{"title": "Supermarkt", "key": "Supermarket", "icon": "deu/ShoppingAndService_Supermarket.png"},
{"title": "Plätze", "key": "Squares", "icon": "deu/CulturalActivity_Squares.png"},
{"title": "Verkaufsstelle für Bustickets", "key": "Bus_tickets_retail", "icon": "deu/TransferServiceAndRenting_Bus_tickets_retail.png"},
{"title": "Botanische Gärten und Zoos", "key": "Botanical_and_zoological_gardens", "icon": "deu/CulturalActivity_Botanical_and_zoological_gardens.png"},
{"title": "Trambahnlinien", "key": "Tramline", "icon": "deu/TransferServiceAndRenting_Tramline.png"},
{"title": "Bushaltestelle", "key": "BusStop", "icon": "deu/TransferServiceAndRenting_BusStop.png"},
{"title": "Einkaufszentren", "key": "Shopping_centre", "icon": "deu/ShoppingAndService_Shopping_centre.png"},
{"title": "Autoparkplätze", "key": "Car_park", "icon": "deu/TransferServiceAndRenting_Car_park.png"},
{"title": "Informationszentrum für Touristen", "key": "Tourist_information_office", "icon": "deu/TourismService_Tourist_information_office.png"},
{"title": "Betreuungsstelle für Touristen", "key": "Travel_information", "icon": "deu/TourismService_Travel_information.png"},
{"title": "Bank", "key": "Bank", "icon": "deu/FinancialService_Bank.png"},
{"title": "Trambahnhaltestellen", "key": "Tram_stops", "icon": "deu/TransferServiceAndRenting_Tram_stops.png"},
{"title": "Minimarkt", "key": "Minimarket", "icon": "deu/ShoppingAndService_Minimarket.png"},
{"title": "Hotel", "key": "Hotel", "icon": "deu/Accommodation_Hotel.png"},
{"title": "Wifi", "key": "Wifi", "icon": "deu/TourismService_Wifi.png"},
{"title": "Weinladen und Weinlokal", "key": "Wine_shop_and_wine_bar", "icon": "deu/WineAndFood_Wine_shop_and_wine_bar.png"},
{"title": "Toiletten", "key": "Toilet", "icon": "deu/TourismService_Toilet.png"},
{"title": "Trinkbrunnen", "key": "Drinking_fountain", "icon": "deu/WineAndFood_Drinking_fountain.png"},
{"title": "Carabinieri (Polizei)", "key": "Carabinieri", "icon": "deu/Emergency_Carabinieri.png"},
{"title": "Stadtführer", "key": "Tourist_guides", "icon": "deu/TourismService_Tourist_guides.png"},
{"title": "Büro für geführte Touren", "key": "Travel_bureau", "icon": "deu/TourismService_Travel_bureau.png"},
{"title": "Bahnhöfe", "key": "Train_station", "icon": "deu/TransferServiceAndRenting_Train_station.png"},
{"title": "Beschwerdestelle für Touristen", "key": "Tourist_complaints_office", "icon": "deu/TourismService_Tourist_complaints_office.png"},
{"title": "Konsulat", "key": "Consulate", "icon": "deu/GovernmentOffice_Consulate.png"},
{"title": "Notaufnahme", "key": "First_aid", "icon": "deu/Emergency_First_aid.png"},
{"title": "Apotheke", "key": "Pharmacy", "icon": "deu/ShoppingAndService_Pharmacy.png"},
{"title": "Agrartourismus", "key": "Agriturism", "icon": "deu/Accommodation_Agriturism.png"},
{"title": "Bed And Breakfast", "key": "Bed_and_breakfast", "icon": "deu/Accommodation_Bed_and_breakfast.png"},
{"title": "Internet Point", "key": "Internet_point_and_public_telephone", "icon": "deu/UtilitiesAndSupply_Internet_point_and_public_telephone.png"},
{"title": "Taxiunternehmen", "key": "Taxi_company", "icon": "deu/TransferServiceAndRenting_Taxi_company.png"},
{"title": "Highlights für Touristen", "key": "Tourist_trail", "icon": "deu/TourismService_Tourist_trail.png"},
{"title": "Fahrradverleih", "key": "Bike_rental", "icon": "deu/TransferServiceAndRenting_Bike_rental.png"},
{"title": "Gemeindepolizei", "key": "Local_police", "icon": "deu/Emergency_Local_police.png"}
]