[
{"title": "Parada de autobús", "key": "BusStop", "icon": "esp/TransferServiceAndRenting_BusStop.png"},
{"title": "Pizzería", "key": "Pizzeria", "icon": "esp/WineAndFood_Pizzeria.png"},
{"title": "Trattoría", "key": "Trattoria", "icon": "esp/WineAndFood_Trattoria.png"},
{"title": "Oficina de Correos", "key": "Postal_office", "icon": "esp/GovernmentOffice_Postal_office.png"},
{"title": "Restaurante", "key": "Restaurant", "icon": "esp/WineAndFood_Restaurant.png"},
{"title": "Farmacia", "key": "Pharmacy", "icon": "esp/ShoppingAndService_Pharmacy.png"},
{"title": "Jardines", "key": "Gardens", "icon": "esp/Entertainment_Gardens.png"},
{"title": "Librería", "key": "Bookshop", "icon": "esp/ShoppingAndService_Bookshop.png"},
{"title": "Paradas de tranvía", "key": "Tram_stops", "icon": "esp/TransferServiceAndRenting_Tram_stops.png"},
{"title": "Urgencias médicas", "key": "Emergency_medical_care", "icon": "esp/Emergency_Emergency_medical_care.png"},
{"title": "Carril bici", "key": "Cycle_paths", "icon": "esp/TransferServiceAndRenting_Cycle_paths.png"},
{"title": "Supermercado", "key": "Supermarket", "icon": "esp/ShoppingAndService_Supermarket.png"},
{"title": "Instalaciones deportivas", "key": "Sports_facility", "icon": "esp/Entertainment_Sports_facility.png"},
{"title": "Banca", "key": "Bank", "icon": "esp/FinancialService_Bank.png"},
{"title": "Policía", "key": "Carabinieri", "icon": "esp/Emergency_Carabinieri.png"},
{"title": "Piscina", "key": "Pool", "icon": "esp/Entertainment_Pool.png"},
{"title": "Primeros auxilios", "key": "First_aid", "icon": "esp/Emergency_First_aid.png"},
{"title": "Cine", "key": "Cinema", "icon": "esp/Entertainment_Cinema.png"},
{"title": "Línea de tranvía", "key": "Tramline", "icon": "esp/TransferServiceAndRenting_Tramline.png"},
{"title": "Aparcamiento", "key": "Car_park", "icon": "esp/TransferServiceAndRenting_Car_park.png"},
{"title": "Aparcamiento de bicicletas", "key": "Bike_rack", "icon": "esp/TransferServiceAndRenting_Bike_rack.png"},
{"title": "Venta de billetes de autobús", "key": "Bus_tickets_retail", "icon": "esp/TransferServiceAndRenting_Bus_tickets_retail.png"},
{"title": "Hipermercados", "key": "Hypermarket", "icon": "esp/ShoppingAndService_Hypermarket.png"},
{"title": "Casa de apuestas", "key": "Betting_shops", "icon": "esp/Entertainment_Betting_shops.png"},
{"title": "Dentista", "key": "Dentist", "icon": "esp/HealthCare_Dentist.png"},
{"title": "Policía local", "key": "Local_police", "icon": "esp/Emergency_Local_police.png"},
{"title": "Emergencias", "key": "Emergency_services", "icon": "esp/Emergency_Emergency_services.png"},
{"title": "Colegios de educación primaria", "key": "Primary_education", "icon": "esp/EducationAndResearch_Primary_education.png"},
{"title": "Bomberos", "key": "Fire_brigade", "icon": "esp/Emergency_Fire_brigade.png"},
{"title": "Seguridad social", "key": "Social_security_service_office", "icon": "esp/GovernmentOffice_Social_security_service_office.png"},
{"title": "Autoridad sanitaria", "key": "Local_health_authority", "icon": "esp/HealthCare_Local_health_authority.png"},
{"title": "Hospital público", "key": "Public_hospital", "icon": "esp/HealthCare_Public_hospital.png"},
{"title": "Teatros", "key": "Theatre", "icon": "esp/CulturalActivity_Theatre.png"},
{"title": "Registro Civil", "key": "Civil_registry_and_other_office", "icon": "esp/GovernmentOffice_Civil_registry_and_other_office.png"},
{"title": "Centro de Salud", "key": "Group_practice", "icon": "esp/HealthCare_Group_practice.png"},
{"title": "Gimnasio", "key": "Gym_fitness", "icon": "esp/Entertainment_Gym_fitness.png"},
{"title": "Aduanas", "key": "Income_revenue_authority", "icon": "esp/GovernmentOffice_Income_revenue_authority.png"},
{"title": "Institutos privados", "key": "Private_junior_high_school", "icon": "esp/EducationAndResearch_Private_junior_high_school.png"},
{"title": "Guarderías privadas", "key": "Private_preschool", "icon": "esp/EducationAndResearch_Private_preschool.png"},
{"title": "Institutos públicos", "key": "Public_junior_high_school", "icon": "esp/EducationAndResearch_Public_junior_high_school.png"}

]